pygrocy2/__init__.py
pygrocy2/base.py
pygrocy2/grocy.py
pygrocy2/grocy_api_client.py
pygrocy2/utils.py
pygrocy2/data_models/__init__.py
pygrocy2/data_models/battery.py
pygrocy2/data_models/chore.py
pygrocy2/data_models/generic.py
pygrocy2/data_models/meal_items.py
pygrocy2/data_models/product.py
pygrocy2/data_models/system.py
pygrocy2/data_models/task.py
pygrocy2/data_models/user.py
pygrocy2/errors/__init__.py
pygrocy2/errors/grocy_error.py
pygrocy2-2.6.0.dist-info/licenses/LICENSE
pygrocy2-2.6.0.dist-info/METADATA
pygrocy2-2.6.0.dist-info/WHEEL
pygrocy2-2.6.0.dist-info/top_level.txt
pygrocy2-2.6.0.dist-info/RECORD
