Metadata-Version: 2.4
Name: pygrocy2
Version: 2.6.0
Author-email: George Green <iamkarlson@gmail.com>
License-Expression: MIT
Project-URL: Homepage, https://github.com/iamkarlson/pygrocy2
Requires-Python: >=3.12
License-File: LICENSE
Requires-Dist: requests
Requires-Dist: deprecation~=2.1.0
Requires-Dist: pydantic~=2.12.2
Requires-Dist: tzdata
Requires-Dist: tzlocal~=5.2
Dynamic: license-file
